examples/basic.py
examples/dataframes.py
sparkmonitoring/__init__.py
sparkmonitoring/api.py
sparkmonitoring/dataframes.py
sparkmonitoring/responsetype.py
spark_monitoring-0.0.3.dist-info/LICENSE
spark_monitoring-0.0.3.dist-info/METADATA
spark_monitoring-0.0.3.dist-info/WHEEL
spark_monitoring-0.0.3.dist-info/top_level.txt
spark_monitoring-0.0.3.dist-info/RECORD
