Metadata-Version: 2.1
Name: spark-monitoring
Version: 0.0.3
Summary: A python library to interact with the Spark History server
Home-page: https://bliseng.github.io/spark-monitoring/
Author: Drew J. Sonne
Author-email: drew.sonne@gmail.com
License: LGPL3
Platform: UNKNOWN
Requires-Dist: requests
